<?xml version="1.0" encoding="UTF-8"?>
<persistence version="2.1" xmlns="http://xmlns.jcp.org/xml/ns/persistence" xmlns:xsi="http://www.w3.org/2001/XMLSchema-instance" xsi:schemaLocation="http://xmlns.jcp.org/xml/ns/persistence http://xmlns.jcp.org/xml/ns/persistence/persistence_2_1.xsd">
  <persistence-unit name="JpaHowItWorksPU" transaction-type="RESOURCE_LOCAL">
    <provider>org.eclipse.persistence.jpa.PersistenceProvider</provider>
    <class>fon.silab.njt.jpa.howitworks.entity.CityEntity</class>
    <class>fon.silab.njt.jpa.howitworks.entity.ProductCategoryEntity</class>
    <class>fon.silab.njt.jpa.howitworks.entity.ManufacturerEntity</class>
    <class>fon.silab.njt.jpa.howitworks.entity.ContactPersonEntity</class>
    <class>fon.silab.njt.jpa.howitworks.entity.ProductEntity</class>
    <class>fon.silab.njt.jpa.howitworks.entity.inheritance.BusinessPartnerEntity</class>
    <class>fon.silab.njt.jpa.howitworks.entity.inheritance.LegalEntity</class>
    <class>fon.silab.njt.jpa.howitworks.entity.inheritance.NaturalEntity</class>
    <properties>
      <property name="javax.persistence.jdbc.url" value="jdbc:mysql://localhost:3306/jpahowitworks?serverTimezone=UTC"/>
      <property name="javax.persistence.jdbc.user" value="admin"/>
      <property name="javax.persistence.jdbc.driver" value="com.mysql.cj.jdbc.Driver"/>
      <property name="javax.persistence.jdbc.password" value="admin"/>
      <!-- CREATE TABLE -->
      <property name="javax.persistence.schema-generation.database.action" value="create"/>
    </properties>
  </persistence-unit>
</persistence>
